udmp_parser-stubs/__init__.pyi
udmp_parser-stubs/utils.pyi
udmp_parser.cp313-win32.pyd
udmp_parser-0.7.0.dist-info/METADATA
udmp_parser-0.7.0.dist-info/WHEEL
udmp_parser-0.7.0.dist-info/entry_points.txt
udmp_parser-0.7.0.dist-info/RECORD
