Metadata-Version: 2.1
Name: udmp-parser
Version: 0.7.0
Summary: A Cross-Platform C++ parser library for Windows user minidumps.
Author-Email: 0vercl0k <0vercl0k@not-your-biz.net>
Classifier: Development Status :: 4 - Beta
Classifier: License :: OSI Approved :: MIT License
Classifier: Programming Language :: Python :: 3
Classifier: Programming Language :: Python :: 3.8
Classifier: Programming Language :: Python :: 3.9
Classifier: Programming Language :: Python :: 3.10
Classifier: Programming Language :: Python :: 3.11
Classifier: Programming Language :: Python :: 3.12
Classifier: Topic :: Software Development :: Assemblers
Classifier: Natural Language :: English
Project-URL: Homepage, https://github.com/0vercl0k/udmp-parser
Requires-Python: >=3.8
